[
  {
    "url": "//www.youtube.com/watch?v=P-B_q2bxldI",
    "title": "Episode 1: Hybrid blockchain",
    "category": "Nexus Developers",
    "image": "episode1.jpg",
    "tags": [{ "name": "Hybrid" }, { "name": "Blockchain" }]
  },
  {
    "url": "//www.youtube.com/watch?v=70KfDhr0c_4",
    "title": "Episode 2: Contract DSL",
    "category": "Nexus Developers",
    "image": "episode2.jpg",
    "tags": [{ "name": "Smart Contract" }]
  },
  {
    "url": "//www.youtube.com/watch?v=GGE3gBBYLM4",
    "title": "Episode 3: Register Layer",
    "category": "Nexus Developers",
    "image": "episode3.jpg",
    "tags": [{ "name": "Register" }, { "name": "Smart Contract" }]
  },
  {
    "url": "//www.youtube.com/watch?v=CGuwE__-tI4",
    "title": "Episode 4: Dapp Reverse Proxy Authentication",
    "category": "Nexus Developers",
    "image": "episode4.jpg",
    "tags": [{ "name": "WEB3" }, { "name": "Authentication" }]
  },
  {
    "url": "//www.youtube.com/watch?v=xpLZhHmgWKY",
    "title": "Episode 5: Module Store",
    "category": "Nexus Developers",
    "image": "episode5.jpg",
    "tags": [{ "name": "WEB3" }]
  },
  {
    "url": "//www.youtube.com/watch?v=DmESBYwrwEE&",
    "title": "Episode 6: P2P Marketplace",
    "category": "Nexus Developers",
    "image": "episode6.jpg",
    "tags": [{ "name": "DEX" }, { "name": "P2P" }]
  },
  {
    "url": "//www.youtube.com/watch?v=Y9sKgWRfBvY",
    "title": "Episode 7: Signature Chain Access",
    "category": "Nexus Developers",
    "image": "episode7.jpg",
    "tags": [{ "name": "WEB3" }]
  },
  {
    "url": "//www.youtube.com/watch?v=Lrx3QhSH9sc",
    "title": "Episode 8: Decentralized GitHub",
    "category": "Nexus Developers",
    "image": "episode8.jpg",
    "tags": [{ "name": "WEB3" }]
  },
  {
    "url": "//www.youtube.com/watch?v=Tw9gtwpB39s",
    "title": "Episode 9: LISP",
    "category": "Nexus Developers",
    "image": "episode9.jpg",
    "tags": [{ "name": "LISP" }]
  },
  {
    "url": "//www.youtube.com/watch?v=YzK4NinDjDo",
    "title": "Episode 10: TAO Framework",
    "category": "Nexus Developers",
    "image": "episode10.jpg",
    "tags": [{ "name": "WEB3" }]
  },
  {
    "url": "//www.youtube.com/watch?v=m_uMmhCIvso",
    "title": "Episode 11: Ticketing with Assets",
    "category": "Nexus Developers",
    "image": "episode11.jpg",
    "tags": [{ "name": "Assets" }]
  },
  {
    "url": "//www.youtube.com/watch?v=rqWOfuSaYmo",
    "title": "Episode 12: Nexus Virtual Machine",
    "category": "Nexus Developers",
    "image": "episode12.jpg",
    "tags": [{ "name": "EVM" }, { "name": "WEB3" }]
  },
  {
    "url": "//www.youtube.com/watch?v=1nEQBscO9LQ",
    "title": "Episode 13: Mobile Wallet",
    "category": "Nexus Developers",
    "image": "episode13.jpg",
    "tags": [{ "name": "WEB3" }]
  },
  {
    "url": "//www.youtube.com/watch?v=J0yIxjPLkXs",
    "title": "Episode 14: Satellite Routing Services",
    "category": "Nexus Developers",
    "image": "episode14.jpg",
    "tags": []
  },
  {
    "url": "//www.youtube.com/watch?v=ehthZ8J4ppM",
    "title": "Episode 15: Satellites SDR",
    "category": "Nexus Developers",
    "image": "episode15.jpg",
    "tags": [{ "name": "WEB3" }]
  },
  {
    "url": "//www.youtube.com/watch?v=ehthZ8J4ppM",
    "title": "Episode 15: Satellites SDR",
    "category": "Nexus Developers",
    "image": "episode15.jpg",
    "tags": [{ "name": "WEB3" }]
  },
  {
    "url": "//www.youtube.com/watch?v=Vq3sJe5AP9c",
    "title": "Episode 16: Satellite Support",
    "category": "Nexus Developers",
    "image": "episode16.jpg",
    "tags": [{ "name": "WEB3" }]
  },
  {
    "url": "//www.youtube.com/watch?v=qTAqNF1qCzQ",
    "title": "Episode 17: Identity Arbitration",
    "category": "Nexus Developers",
    "image": "episode17.jpg",
    "tags": []
  },
  {
    "url": "//www.youtube.com/watch?v=GpUHGHExAOs",
    "title": "Episode 18: Internet, What's Next",
    "category": "Nexus Developers",
    "image": "episode18.jpg",
    "tags": []
  },
  {
    "url": "//www.youtube.com/watch?v=Iyk-lDkctow",
    "title": "Episode 19: Decentralized Systems & Global Law",
    "category": "Nexus Developers",
    "image": "episode19.jpg",
    "tags": [{ "name": "WEB3" }]
  },
  {
    "url": "//www.youtube.com/watch?v=R5uoz5ZeKjY",
    "title": "Episode 20: Starfish Base Voting Layer",
    "category": "Nexus Developers",
    "image": "episode20.jpg",
    "tags": [{ "name": "WEB3" }, { "name": "DAO" }]
  },
  {
    "url": "//www.youtube.com/watch?v=I4Bvs_lpHZI",
    "title": "Episode 21: Scaling Bitcoin",
    "category": "Nexus Developers",
    "image": "episode21.jpg",
    "tags": [{ "name": "BTC" }]
  },
  {
    "url": "//www.youtube.com/watch?v=wkecEA2gtRI",
    "title": "Episode 22: Internet of Things",
    "category": "Nexus Developers",
    "image": "episode22.jpg",
    "tags": [{ "name": "IOT" }, { "name": "WEB3" }]
  },
  {
    "url": "//www.youtube.com/watch?v=ABvyQBG0KJk",
    "title": "Episode 23: Supply Chain, Collateralized Transport",
    "category": "Nexus Developers",
    "image": "episode23.jpg",
    "tags": []
  },
  {
    "url": "//www.youtube.com/watch?v=oPprRtuzXHw",
    "title": "Episode 24: Decentralized ATM Network",
    "category": "Nexus Developers",
    "image": "episode24.jpg",
    "tags": []
  },
  {
    "url": "//www.youtube.com/watch?v=dEU3h2SqOwc",
    "title": "Episode 25: Tokens",
    "category": "Nexus Developers",
    "image": "episode25.jpg",
    "tags": [{ "name": "Tokens" }]
  }
]
